chorny
