Metadata-Version: 2.1
Name: chorny
Version: 1.3.0
Summary: Loader of Black to ensure Athenian's code formatting conventions.
Home-page: https://github.com/athenian/chorny
Author: Athenian
Author-email: vadim@athenian.co
License: MIT
Keywords: black
Platform: UNKNOWN
Classifier: Development Status :: 3 - Alpha
Classifier: Programming Language :: Python :: 3.8
Classifier: Programming Language :: Python :: 3.9
Classifier: Programming Language :: Python :: 3.10
Classifier: License :: OSI Approved :: MIT License
